{"nodes": [{"id": "bootstrap_substrate_sh", "label": "bootstrap substrate phase", "file_type": "code", "source_file": "factory/utilities/bootstrap/substrate.sh", "source_location": null, "source_url": null, "captured_at": null, "author": null, "contributor": null, "rationale": "Provisions the cluster-level platform hosting the factory: Crossplane XRDs/Compositions/providers/RBAC, Argo Workflows server config, Argo Events sensors+OAM webhook, ArgoCD, and Knative Serving. Idempotent."}], "edges": [{"source": "bootstrap_substrate_sh", "target": "bootstrap_helpers_common_sh", "relation": "references", "confidence": "EXTRACTED", "confidence_score": 1.0, "source_file": "factory/utilities/bootstrap/substrate.sh", "source_location": null, "weight": 1.0}, {"source": "bootstrap_substrate_sh", "target": "bootstrap_helpers_common_apply_dir", "relation": "calls", "confidence": "EXTRACTED", "confidence_score": 1.0, "source_file": "factory/utilities/bootstrap/substrate.sh", "source_location": null, "weight": 1.0}], "hyperedges": []}