{"nodes": [{"id": "tests_test_cue_param_parser", "label": "test_cue_param_parser", "file_type": "code", "source_file": "factory/shared-libs/capability-mcp-core/tests/test_cue_param_parser.py", "source_location": null, "source_url": null, "captured_at": null, "author": null, "contributor": null}], "edges": [{"source": "tests_test_cue_param_parser", "target": "cue_param_parser_parse_parameter_block", "relation": "references", "confidence": "EXTRACTED", "confidence_score": 1.0, "source_file": "factory/shared-libs/capability-mcp-core/tests/test_cue_param_parser.py", "source_location": null, "weight": 1.0}], "hyperedges": []}